{"cameraMode":{"drawMode":0,"name":"Shaded","section":"Shading Mode"},"sceneLighting":true,"audioPlay":false,"sceneViewState":{"m_AlwaysRefresh":false,"showFog":true,"showSkybox":true,"showFlares":true,"showImageEffects":true,"showParticleSystems":true,"showVisualEffectGraphs":true,"m_FxEnabled":true},"in2DMode":false,"pivot":{"x":-2.820136070251465,"y":2.2105488777160646,"z":4.21599006652832},"rotation":{"x":-0.2813996374607086,"y":0.018981346860527993,"z":-0.0055675446055829529,"w":-0.959388017654419},"size":9.737138748168946,"orthographic":false}